{
  "name": "github_delete_org_secret_scanning_custom_patterns",
  "description": "Bulk delete custom patterns (DELETE /orgs/{org}/secret-scanning/custom-patterns).",
  "arguments": {
    "type": "object",
    "properties": {
      "org": {
        "type": "string",
        "minLength": 1,
        "maxLength": 39
      },
      "patterns": {
        "type": "array",
        "items": {
          "type": "object",
          "properties": {
            "pattern_id": {
              "type": "integer",
              "minimum": 1
            },
            "custom_pattern_version": {
              "type": [
                "string",
                "null"
              ]
            }
          },
          "required": [
            "pattern_id"
          ]
        }
      },
      "post_delete_action": {
        "type": "string",
        "enum": [
          "delete_alerts",
          "resolve_alerts"
        ]
      }
    },
    "required": [
      "org",
      "patterns"
    ],
    "$schema": "http://json-schema.org/draft-07/schema#"
  }
}
